feynpy/__init__.py
feynpy-0.0.2.dist-info/LICENSE
feynpy-0.0.2.dist-info/METADATA
feynpy-0.0.2.dist-info/WHEEL
feynpy-0.0.2.dist-info/top_level.txt
feynpy-0.0.2.dist-info/RECORD
