Metadata-Version: 2.1
Name: feynpy
Version: 0.0.2
Summary: Python package for QFT calculations
Author-email: FeynPy <feynpy@email.cz>
Project-URL: Homepage, https://github.com/FeynPy/feynpy
Project-URL: Issues, https://github.com/FeynPy/feynpy/issues
Classifier: Programming Language :: Python :: 3
Classifier: License :: OSI Approved :: GNU General Public License v3 or later (GPLv3+)
Classifier: Operating System :: OS Independent
Requires-Python: >=3.8
License-File: LICENSE
